t2py/__init__.py
t2py/titan2.py
t2py-0.1.1.dist-info/METADATA
t2py-0.1.1.dist-info/WHEEL
t2py-0.1.1.dist-info/licenses/LICENSE
t2py-0.1.1.dist-info/RECORD
